Workbook

Sheet Inputs
A1: ROI INPUTS · Yellow cells = edit these
A3: Plant & Line Economics
A4: Vehicles produced per day (single line) | B4: 1600 | D4: Ulsan single line, 2 shifts. ~400K/yr per line.
A5: Production days per year | B5: 300 | D5: ~6 days/week, planned shutdowns excluded.
A6: Average vehicle revenue (USD) | B6: 30000 | D6: Mix of Tucson, Santa Fe, IONIQ — use your blended ASP.
A7: Average warranty cost per defect escape (USD) | B7: 450 | D7: Industry-standard $300–$800 depending on defect class.
A8: Average rework cost per defect (USD) | B8: 180 | D8: Includes labor + materials + line disruption.
A9: Hourly fully-loaded line labor cost (USD) | B9: 95 | D9: Per operator, includes benefits.
A10: Unplanned downtime cost per minute (USD) | B10: 22000 | D10: Industry-standard for high-volume automotive line.
A11: Current unplanned downtime (hrs / week) | B11: 6.4 | D11: Default from Global EV manufacturer baseline.
A12: Current defect escape rate (% of vehicles) | B12: 0.012 | D12: 1.2% — typical pre-AI baseline.
A13: Current rework rate (% of vehicles) | B13: 0.08 | D13: 8% pre-AI typical on premium SUV lines.
A14: Discount rate (for NPV) | B14: 0.1 | D14: Standard corporate discount rate.
A16: Pilot Economics — PeopleTech engagement
A17: Pilot duration (weeks) | B17: 12 | D17: Discovery + delivery + measurement.
A18: Pilot fixed fee per use case (USD) | B18: 450000 | D18: PeopleTech embedded pod, fixed-scope.
A19: Per-line scale rollout cost (USD) | B19: 200000 | D19: Hardware + integration per additional line.
A20: Annual managed-service / Run cost (USD) | B20: 180000 | D20: Drift monitoring, retraining, 24×7 support per pilot.
A21: Number of lines / assets in full rollout | B21: 8 | D21: How many lines (Visual Inspection) or asset groups (PM) to scale to.

Sheet Pilot Sizing
A1: PILOT SIZING · Two Recommended Pilots
A3: Pilot 1 — AI-based Visual Inspection (Recommended: HMGMA paint, IONIQ line)
A4: Metric | B4: Baseline | C4: With AI | D4: Annual Value | E4: Logic
A5: Defect escapes per year | B5: =Inputs!$B$4*Inputs!$B$5*Inputs!$B$12 | C5: =Inputs!$B$4*Inputs!$B$5*Inputs!$B$12*(1-0.60) | D5: =(B5-C5)*Inputs!$B$7 | E5: −60% escape defects (deck benchmark)
A6: Rework events per year | B6: =Inputs!$B$4*Inputs!$B$5*Inputs!$B$13 | C6: =Inputs!$B$4*Inputs!$B$5*Inputs!$B$13*(1-0.45) | D6: =(B6-C6)*Inputs!$B$8 | E6: −45% rework cost (deck benchmark)
A7: Manual inspection labor (annualized USD) | B7: =4*Inputs!$B$9*8*Inputs!$B$5 | C7: =2*Inputs!$B$9*8*Inputs!$B$5 | D7: =B7-C7 | E7: 4 inspectors → 2 supervisors per shift
A9: Annual Value per Line (Pilot 1) | D9: =SUM(D5:D7)
A10: Year-1 Investment (1 pilot) | D10: =Inputs!$B$18
A11: Year-1 ROI (single-line pilot) | D11: =D9/D10
A12: Payback (months) | D12: =D10/(D9/12)
A13: Scaled value (full rollout, annual) | D13: =D9*Inputs!$B$21
A15: Pilot 2 — Predictive Maintenance (Recommended: Ulsan stamping + Asan welding)
A16: Metric | B16: Baseline | C16: With AI | D16: Annual Value | E16: Logic
A17: Unplanned downtime (hrs / year) | B17: =Inputs!$B$11*52 | C17: =Inputs!$B$11*52*(1-0.40) | D17: =(B17-C17)*60*Inputs!$B$10 | E17: −40% unplanned downtime (deck benchmark, 5:1 ROI)
A18: Reactive maintenance cost (annualized USD) | B18: =12*8*Inputs!$B$9*52 | C18: =12*8*Inputs!$B$9*52*(1-0.30) | D18: =B18-C18 | E18: −30% maintenance cost
A19: Asset lifespan extension (annualized USD) | B19: =2500000 | C19: =2500000*(1+0.25) | D19: =C19-B19 | E19: +25% asset lifespan amortized over $2.5M typical asset
A21: Annual Value per Line/Asset Group (Pilot 2) | D21: =SUM(D17:D19)
A22: Year-1 Investment (1 pilot) | D22: =Inputs!$B$18
A23: Year-1 ROI (single-pilot) | D23: =D21/D22
A24: Payback (months) | D24: =D22/(D21/12)
A25: Scaled value (full rollout, annual) | D25: =D21*Inputs!$B$21
A27: Combined 3-Year NPV — Both Pilots Scaled
A28: Year | B28: Investment | C28: Annual Value | D28: Net Cashflow | E28: Discounted
A29: Year 1 (Pilots + initial scale) | B29: =2*Inputs!$B$18+Inputs!$B$19*Inputs!$B$21 | C29: =(D13+D25)/2 | D29: =C29-B29 | E29: =D29/((1+Inputs!$B$14)^1)
A30: Year 2 (Full operation) | B30: =2*Inputs!$B$20 | C30: =D13+D25 | D30: =C30-B30 | E30: =D30/((1+Inputs!$B$14)^2)
A31: Year 3 (Full operation) | B31: =2*Inputs!$B$20 | C31: =D13+D25 | D31: =C31-B31 | E31: =D31/((1+Inputs!$B$14)^3)
A33: 3-YEAR NPV (BOTH PILOTS, SCALED) | E33: =SUM(E29:E31)

Sheet Full Use Cases
A1: ALL 8 USE CASES · Per-Line Annual Value Estimates
A3: Use Case | B3: Driver (per line) | C3: Improvement % | D3: Baseline Cost | E3: Annual Value | F3: Scaled (× lines) | G3: Hyundai Anchor
A4: UC-01 Visual Inspection | B4: Escape defect warranty cost | C4: 0.6 | D4: =Inputs!$B$4*Inputs!$B$5*Inputs!$B$12*Inputs!$B$7 | E4: =C4*D4 | F4: =E4*Inputs!$B$21 | G4: HMGMA · IONIQ paint shop
A5: UC-02 Variant Confirmation | B5: Wrong-variant rework events | C5: 0.7 | D5: =Inputs!$B$4*Inputs!$B$5*0.005*Inputs!$B$8*4 | E5: =C5*D5 | F5: =E5*Inputs!$B$21 | G5: High-variant Tucson trim lines · Genesis
A6: UC-03 Seating & Component Validation | B6: Fitment-related recall risk | C6: 0.85 | D6: =2000000 | E6: =C6*D6 | F6: =E6*Inputs!$B$21 | G6: Final assembly · all passenger lines
A7: UC-04 SOP Compliance | B7: Final-stage defect leakage | C7: 0.4 | D7: =Inputs!$B$4*Inputs!$B$5*0.008*Inputs!$B$7 | E7: =C7*D7 | F7: =E7*Inputs!$B$21 | G7: Complex assembly cells · Genesis
A8: UC-05 Predictive Quality | B8: Scrap + rework cost | C8: 0.35 | D8: =Inputs!$B$4*Inputs!$B$5*Inputs!$B$13*Inputs!$B$8 | E8: =C8*D8 | F8: =E8*Inputs!$B$21 | G8: Body-in-white · welding shops
A9: UC-06 Predictive Maintenance | B9: Unplanned downtime cost | C9: 0.4 | D9: =Inputs!$B$11*52*60*Inputs!$B$10 | E9: =C9*D9 | F9: =E9*Inputs!$B$21 | G9: Ulsan stamping · Asan welding
A10: UC-07 Safety Monitoring | B10: Incident + EHS exposure | C10: 0.55 | D10: =1500000 | E10: =C10*D10 | F10: =E10*Inputs!$B$21 | G10: Plant-wide · HMMA / HMI / HMMC rollout pattern
A11: UC-08 Digital Traceability | B11: Recall investigation + audit | C11: 0.7 | D11: =3000000 | E11: =C11*D11 | F11: =E11*Inputs!$B$21 | G11: Cross-plant supply chain · component genealogy
A13: TOTAL — All 8 Use Cases, Scaled | E13: =SUM(E4:E11) | F13: =SUM(F4:F11)

Sheet Notes
A1: ASSUMPTIONS · SOURCES · SENSITIVITY
A4: PURPOSE
A5: This workbook lets Hyundai stakeholders enter their own line economics and see the resulting
A6: ROI for the two recommended pilots (Visual Inspection + Predictive Maintenance) and for all
A7: eight use cases in the AI for Plant Operations deck. Yellow cells in the Inputs tab are editable.
A8: All other cells are formulas.
A10: DEFAULT VALUES — SOURCES
A11: • Vehicles per day (1,600) — single high-volume line at Ulsan-scale plant; ~400K vehicles/year per line.
A12: • Production days (300) — standard automotive year less planned shutdowns.
A13: • Downtime cost ($22,000/min) — automotive industry standard for high-volume final-assembly lines.
A14: • Downtime baseline (6.4 hrs/week) — anchored on the Global EV manufacturer reference case from the deck.
A15: • Defect escape rate (1.2%) and rework rate (8%) — pre-AI baselines from Tier-1 OEM paint shop reference case.
... A34: sheets recalculate live. Make the recommendation feel inevitable: 'These are your numbers, not ours.'
